manageadmins/__init__.py
manageadmins/management/__init__.py
manageadmins/management/commands/__init__.py
manageadmins/management/commands/disable_user.py
manageadmins/management/commands/list_staff.py
manageadmins/management/commands/list_superusers.py
django_manage_admins-0.1.0.dist-info/METADATA
django_manage_admins-0.1.0.dist-info/WHEEL
django_manage_admins-0.1.0.dist-info/top_level.txt
django_manage_admins-0.1.0.dist-info/RECORD
